MANIFEST.in
README.md
setup.py
test_easyocr.py
mg_ocr.egg-info/PKG-INFO
mg_ocr.egg-info/SOURCES.txt
mg_ocr.egg-info/dependency_links.txt
mg_ocr.egg-info/requires.txt
mg_ocr.egg-info/top_level.txt
mgocr/__init__.py
mgocr/cnocr/__init__.py
mgocr/cnocr/__version__.py
mgocr/cnocr/cn_ocr.py
mgocr/cnocr/consts.py
mgocr/cnocr/detect_result.py
mgocr/cnocr/line_split.py
mgocr/cnocr/utils.py
mgocr/cnocr/data_utils/__init__.py
mgocr/cnocr/data_utils/aug.py
mgocr/cnocr/data_utils/captcha_generator.py
mgocr/cnocr/data_utils/data_iter.py
mgocr/cnocr/data_utils/multiproc_data.py
mgocr/cnocr/fit/__init__.py
mgocr/cnocr/fit/ctc_loss.py
mgocr/cnocr/fit/ctc_metrics.py
mgocr/cnocr/fit/fit.py
mgocr/cnocr/fit/lstm.py
mgocr/cnocr/hyperparams/__init__.py
mgocr/cnocr/hyperparams/cn_hyperparams.py
mgocr/cnocr/symbols/__init__.py
mgocr/cnocr/symbols/crnn.py
mgocr/cnocr/symbols/densenet.py
mgocr/detection/__init__.py
mgocr/detection/easy_ocr.py