Metadata-Version: 1.2
Name: mg-ocr
Version: 1.0.1
Summary: update torch version dependencies
Home-page: https://github.com/JoeZhou1025/ocr_package
Author: zzh
Author-email: cliffzzh1025@gmail.com
License: MIT
Platform: UNKNOWN
Requires-Python: >=3.5
